[
    {
        "name" : "Arad",
        "longitude" : 49,
        "latitude" : 136,
        "roads" : [
            {"Timisoara": 118},
            {"Sibiu": 140},
            {"Zerind": 75}
        ]
    },
    {
        "name" : "Bucharest",
        "longitude" : 488,
        "latitude" : 371,
        "roads" : [
            {"Fagaras": 211},
            {"Pitesti": 101},
            {"Giurgiu": 90},
            {"Urziceni": 85}
        ]
    },
    {
        "name" : "Craiova",
        "longitude" : 278,
        "latitude" : 427,
        "roads" : [
            {"Pitesti": 138},
            {"Rimnicu Vilcea": 146},
            {"Dobreta": 120}
        ]
    },
    {
        "name" : "Dobreta",
        "longitude" : 154,
        "latitude" : 411,
        "roads" : [
            {"Craiova": 120},
            {"Mehadia": 75}
        ]
    },
    {
        "name" : "Eforie",
        "longitude" : 718,
        "latitude" : 419,
        "roads" : [
            {"Hirsova": 86}
        ]
    },
    {
        "name" : "Fagaras",
        "longitude" : 355,
        "latitude" : 198,
        "roads" : [
            {"Sibiu": 99},
            {"Bucharest": 211}
        ]
    },
    {
        "name" : "Giurgiu",
        "longitude" : 451,
        "latitude" : 451,
        "roads" : [
            {"Bucharest": 90}
        ]
    },
    {
        "name" : "Hirsova",
        "longitude" : 677,
        "latitude" : 339,
        "roads" : [
            {"Eforie": 86},
            {"Urziceni": 98}
        ]
    },
    {
        "name" : "Iasi",
        "longitude" : 593,
        "latitude" : 117,
        "roads" : [
            {"Neamt": 87},
            {"Vasiul": 92}
        ]
    },
    {
        "name" : "Lugoj",
        "longitude" : 154,
        "latitude" : 298,
        "roads" : [
            {"Mehadia": 70},
            {"Timisoara": 111}
        ]
    },
    {
        "name" : "Mehadia",
        "longitude" : 158,
        "latitude" : 354,
        "roads" : [
            {"Lugoj": 70},
            {"Dobreta": 75}
        ]
    },
    {
        "name" : "Neamt",
        "longitude" : 496,
        "latitude" : 73,
        "roads" : [
            {"Iasi": 87}
        ]
    },
    {
        "name" : "Oradea",
        "longitude" : 106,
        "latitude" : 25,
        "roads" : [
            {"Zerind": 71},
            {"Sibiu": 151}
        ]
    },
    {
        "name" : "Pitesti",
        "longitude" : 376,
        "latitude" : 314,
        "roads" : [
            {"Bucharest": 101},
            {"Craiova": 138},
            {"Rimnicu Vilcea": 97}
        ]
    },
    {
        "name" : "Rimnicu Vilcea",
        "longitude" : 250,
        "latitude" : 254,
        "roads" : [
            {"Sibiu": 80},
            {"Craiova": 146},
            {"Pitesti": 97}
        ]
    },
    {
        "name" : "Sibiu",
        "longitude" : 215,
        "latitude" : 186,
        "roads" : [
            {"Arad": 140},
            {"Oradea": 151},
            {"Fagaras": 99},
            {"Rimnicu Vilcea": 80}
        ]
    },
    {
        "name" : "Timisoara",
        "longitude" : 53,
        "latitude" : 254,
        "roads" : [
            {"Arad": 118},
            {"Lugoj": 111}
        ]
    },
    {
        "name" : "Urziceni",
        "longitude" : 569,
        "latitude" : 338,
        "roads" : [
            {"Bucharest": 85},
            {"Hirsova": 98},
            {"Vasiul": 142}
        ]
    },
    {
        "name" : "Vasiul",
        "longitude" : 644,
        "latitude" : 204,
        "roads" : [
            {"Iasi": 92},
            {"Urziceni": 142}
        ]
    },
    {
        "name" : "Zerind",
        "longitude" : 74,
        "latitude" : 81,
        "roads" : [
            {"Arad": 75},
            {"Oradea": 71}
        ]
    }
]
